{
    "sourceFile": "scripts.js",
    "activeCommit": 0,
    "commits": [
        {
            "activePatchIndex": 22,
            "patches": [
                {
                    "date": 1682991564597,
                    "content": "Index: \n===================================================================\n--- \n+++ \n"
                },
                {
                    "date": 1682992324796,
                    "content": "Index: \n===================================================================\n--- \n+++ \n@@ -1,3 +1,18 @@\n function displayMessage() {\r\n-\talert(\"test\");\r\n+\t// get the values of the input fields\r\n+\tvar firstname = document.getElementById(\"firstname\").value;\r\n+\tvar lastname = document.getElementById(\"lastname\").value;\r\n+\r\n+\t// get the values of the selected checkboxes\r\n+\tvar checkboxes = document.querySelectorAll('input[type=\"checkbox\"]:checked');\r\n+\tvar selected = [];\r\n+\tfor (var i = 0; i < checkboxes.length; i++) {\r\n+\t\tselected.push(checkboxes[i].value);\r\n+\t}\r\n+\r\n+\t// construct the message\r\n+\tvar message = \"Hello \" + firstname + \" \" + lastname + \", you have selected the following options: \" + selected.join(\", \");\r\n+\r\n+\t// display the message in an alert box\r\n+\talert(message);\r\n }\r\n"
                },
                {
                    "date": 1682992589122,
                    "content": "Index: \n===================================================================\n--- \n+++ \n@@ -10,9 +10,9 @@\n \t\tselected.push(checkboxes[i].value);\r\n \t}\r\n \r\n \t// construct the message\r\n-\tvar message = \"Hello \" + firstname + \" \" + lastname + \", you have selected the following options: \" + selected.join(\", \");\r\n+\tvar message = \"Hello \" + firstname + \" \" + lastname + \", you have clicked the following boxes: \" + selected.join(\", \");\r\n \r\n \t// display the message in an alert box\r\n \talert(message);\r\n }\r\n"
                },
                {
                    "date": 1682994948697,
                    "content": "Index: \n===================================================================\n--- \n+++ \n@@ -9,10 +9,14 @@\n \tfor (var i = 0; i < checkboxes.length; i++) {\r\n \t\tselected.push(checkboxes[i].value);\r\n \t}\r\n \r\n+\t// get the value of the selected option in the dropdown menu\r\n+\tvar dropdown = document.getElementById(\"dropdown\");\r\n+\tvar selectedOption = dropdown.options[dropdown.selectedIndex].value;\r\n+\r\n \t// construct the message\r\n-\tvar message = \"Hello \" + firstname + \" \" + lastname + \", you have clicked the following boxes: \" + selected.join(\", \");\r\n+\tvar message = \"Hello \" + firstname + \" \" + lastname + \", you have selected the following options: \" + selected.join(\", \") + \". You have also selected \" + selectedOption + \" from the dropdown menu.\";\r\n \r\n \t// display the message in an alert box\r\n \talert(message);\r\n }\r\n"
                },
                {
                    "date": 1682995232604,
                    "content": "Index: \n===================================================================\n--- \n+++ \n@@ -13,10 +13,16 @@\n \t// get the value of the selected option in the dropdown menu\r\n \tvar dropdown = document.getElementById(\"dropdown\");\r\n \tvar selectedOption = dropdown.options[dropdown.selectedIndex].value;\r\n \r\n+\t// create an array of names\r\n+\tvar names = [\"Alice\", \"Bob\", \"Charlie\", \"David\", \"Emma\", \"Frank\", \"Grace\", \"Henry\", \"Isabella\", \"Jack\"];\r\n+\r\n+\t// randomly select a name from the array\r\n+\tvar randomName = names[Math.floor(Math.random() * names.length)];\r\n+\r\n \t// construct the message\r\n-\tvar message = \"Hello \" + firstname + \" \" + lastname + \", you have selected the following options: \" + selected.join(\", \") + \". You have also selected \" + selectedOption + \" from the dropdown menu.\";\r\n+\tvar message = \"Hello \" + firstname + \" \" + lastname + \", you have selected the following options: \" + selected.join(\", \") + \". You have also selected \" + selectedOption + \" from the dropdown menu. Your new name is \" + randomName + \".\";\r\n \r\n \t// display the message in an alert box\r\n \talert(message);\r\n }\r\n"
                },
                {
                    "date": 1682995328044,
                    "content": "Index: \n===================================================================\n--- \n+++ \n@@ -17,12 +17,13 @@\n \t// create an array of names\r\n \tvar names = [\"Alice\", \"Bob\", \"Charlie\", \"David\", \"Emma\", \"Frank\", \"Grace\", \"Henry\", \"Isabella\", \"Jack\"];\r\n \r\n \t// randomly select a name from the array\r\n-\tvar randomName = names[Math.floor(Math.random() * names.length)];\r\n+\tvar randomName1 = names[Math.floor(Math.random() * names.length)];\r\n+    var randomName2 = names[Math.floor(Math.random() * names.length)];\r\n \r\n \t// construct the message\r\n-\tvar message = \"Hello \" + firstname + \" \" + lastname + \", you have selected the following options: \" + selected.join(\", \") + \". You have also selected \" + selectedOption + \" from the dropdown menu. Your new name is \" + randomName + \".\";\r\n+\tvar message = \"Hello \" + firstname + \" \" + lastname + \", you have selected the following options: \" + selected.join(\", \") + \". You have also selected \" + selectedOption + \" from the dropdown menu. Your new name is \" + randomName1 + randomName2;\r\n \r\n \t// display the message in an alert box\r\n \talert(message);\r\n }\r\n"
                },
                {
                    "date": 1682995407610,
                    "content": "Index: \n===================================================================\n--- \n+++ \n@@ -16,14 +16,19 @@\n \r\n \t// create an array of names\r\n \tvar names = [\"Alice\", \"Bob\", \"Charlie\", \"David\", \"Emma\", \"Frank\", \"Grace\", \"Henry\", \"Isabella\", \"Jack\"];\r\n \r\n-\t// randomly select a name from the array\r\n-\tvar randomName1 = names[Math.floor(Math.random() * names.length)];\r\n-    var randomName2 = names[Math.floor(Math.random() * names.length)];\r\n+\t// randomly select two names from the array\r\n+\tvar randomIndex1 = Math.floor(Math.random() * names.length);\r\n+\tvar randomIndex2 = Math.floor(Math.random() * names.length);\r\n+\twhile (randomIndex1 === randomIndex2) {\r\n+\t\trandomIndex2 = Math.floor(Math.random() * names.length);\r\n+\t}\r\n+\tvar randomName1 = names[randomIndex1];\r\n+\tvar randomName2 = names[randomIndex2];\r\n \r\n \t// construct the message\r\n-\tvar message = \"Hello \" + firstname + \" \" + lastname + \", you have selected the following options: \" + selected.join(\", \") + \". You have also selected \" + selectedOption + \" from the dropdown menu. Your new name is \" + randomName1 + randomName2;\r\n+\tvar message = \"Hello \" + firstname + \" \" + lastname + \", you have selected the following options: \" + selected.join(\", \") + \". You have also selected \" + selectedOption + \" from the dropdown menu. Your new names are \" + randomName1 + \" and \" + randomName2 + \".\";\r\n \r\n \t// display the message in an alert box\r\n \talert(message);\r\n }\r\n"
                },
                {
                    "date": 1682995435130,
                    "content": "Index: \n===================================================================\n--- \n+++ \n@@ -26,9 +26,9 @@\n \tvar randomName1 = names[randomIndex1];\r\n \tvar randomName2 = names[randomIndex2];\r\n \r\n \t// construct the message\r\n-\tvar message = \"Hello \" + firstname + \" \" + lastname + \", you have selected the following options: \" + selected.join(\", \") + \". You have also selected \" + selectedOption + \" from the dropdown menu. Your new names are \" + randomName1 + \" and \" + randomName2 + \".\";\r\n+\tvar message = \"Hello \" + firstname + \" \" + lastname + \", you have selected the following options: \" + selected.join(\", \") + \". You have also selected \" + selectedOption + \" from the dropdown menu. Your new names are \" + randomName1 + \" \" + randomName2 + \".\";\r\n \r\n \t// display the message in an alert box\r\n \talert(message);\r\n }\r\n"
                },
                {
                    "date": 1682995494506,
                    "content": "Index: \n===================================================================\n--- \n+++ \n@@ -26,9 +26,9 @@\n \tvar randomName1 = names[randomIndex1];\r\n \tvar randomName2 = names[randomIndex2];\r\n \r\n \t// construct the message\r\n-\tvar message = \"Hello \" + firstname + \" \" + lastname + \", you have selected the following options: \" + selected.join(\", \") + \". You have also selected \" + selectedOption + \" from the dropdown menu. Your new names are \" + randomName1 + \" \" + randomName2 + \".\";\r\n+\tvar message = \"Hello \" + firstname + \" \" + lastname + \", you have selected the following options: \" + selected.join(\", \") + \". You have also selected \" + selectedOption + \" from the dropdown menu. Your new name is \" + randomName1 + \" \" + randomName2 + \".\";\r\n \r\n \t// display the message in an alert box\r\n \talert(message);\r\n }\r\n"
                },
                {
                    "date": 1682996556660,
                    "content": "Index: \n===================================================================\n--- \n+++ \n@@ -26,9 +26,9 @@\n \tvar randomName1 = names[randomIndex1];\r\n \tvar randomName2 = names[randomIndex2];\r\n \r\n \t// construct the message\r\n-\tvar message = \"Hello \" + firstname + \" \" + lastname + \", you have selected the following options: \" + selected.join(\", \") + \". You have also selected \" + selectedOption + \" from the dropdown menu. Your new name is \" + randomName1 + \" \" + randomName2 + \".\";\r\n+\tvar message = \"Hello \" + firstname + \" \" + lastname + \", you are a \" + selected.join(\", \") + \". You have also selected \" + selectedOption + \" from the dropdown menu. Your new name is \" + randomName1 + \" \" + randomName2 + \".\";\r\n \r\n \t// display the message in an alert box\r\n \talert(message);\r\n }\r\n"
                },
                {
                    "date": 1682996917745,
                    "content": "Index: \n===================================================================\n--- \n+++ \n@@ -26,9 +26,9 @@\n \tvar randomName1 = names[randomIndex1];\r\n \tvar randomName2 = names[randomIndex2];\r\n \r\n \t// construct the message\r\n-\tvar message = \"Hello \" + firstname + \" \" + lastname + \", you are a \" + selected.join(\", \") + \". You have also selected \" + selectedOption + \" from the dropdown menu. Your new name is \" + randomName1 + \" \" + randomName2 + \".\";\r\n+\tvar message = \"Hello \" + firstname + \" \" + lastname + \", you are a \" + selected.join(\", \") + \"little jerk. You have also selected \" + selectedOption + \" from the dropdown menu. Your new name is \" + randomName1 + \" \" + randomName2 + \".\";\r\n \r\n \t// display the message in an alert box\r\n \talert(message);\r\n }\r\n"
                },
                {
                    "date": 1682996923575,
                    "content": "Index: \n===================================================================\n--- \n+++ \n@@ -26,9 +26,9 @@\n \tvar randomName1 = names[randomIndex1];\r\n \tvar randomName2 = names[randomIndex2];\r\n \r\n \t// construct the message\r\n-\tvar message = \"Hello \" + firstname + \" \" + lastname + \", you are a \" + selected.join(\", \") + \"little jerk. You have also selected \" + selectedOption + \" from the dropdown menu. Your new name is \" + randomName1 + \" \" + randomName2 + \".\";\r\n+\tvar message = \"Hello \" + firstname + \" \" + lastname + \", you are a \" + selected.join(\", \") + \" little jerk. You have also selected \" + selectedOption + \" from the dropdown menu. Your new name is \" + randomName1 + \" \" + randomName2 + \".\";\r\n \r\n \t// display the message in an alert box\r\n \talert(message);\r\n }\r\n"
                },
                {
                    "date": 1682997485781,
                    "content": "Index: \n===================================================================\n--- \n+++ \n@@ -26,9 +26,9 @@\n \tvar randomName1 = names[randomIndex1];\r\n \tvar randomName2 = names[randomIndex2];\r\n \r\n \t// construct the message\r\n-\tvar message = \"Hello \" + firstname + \" \" + lastname + \", you are a \" + selected.join(\", \") + \" little jerk. You have also selected \" + selectedOption + \" from the dropdown menu. Your new name is \" + randomName1 + \" \" + randomName2 + \".\";\r\n+\tvar message = \"Hello \" + firstname + \" \" + lastname + \", you are a \" + selected.join(\", \") + \" little jerk, and \" + selectedOption + \" . Your new name is \" + randomName1 + \" \" + randomName2 + \".\";\r\n \r\n \t// display the message in an alert box\r\n \talert(message);\r\n }\r\n"
                },
                {
                    "date": 1682999397855,
                    "content": "Index: \n===================================================================\n--- \n+++ \n@@ -14,9 +14,9 @@\n \tvar dropdown = document.getElementById(\"dropdown\");\r\n \tvar selectedOption = dropdown.options[dropdown.selectedIndex].value;\r\n \r\n \t// create an array of names\r\n-\tvar names = [\"Alice\", \"Bob\", \"Charlie\", \"David\", \"Emma\", \"Frank\", \"Grace\", \"Henry\", \"Isabella\", \"Jack\"];\r\n+\tvar names = [\"Smellward\", \"Poopington\", \"Fartsman\", \"Cheesewick\", \"McLoser\", \"Hoobitoob\", \"Cramsworth\", \"Plooperbum\", \"Frimblebim\", \"Feebrizz\"];\r\n \r\n \t// randomly select two names from the array\r\n \tvar randomIndex1 = Math.floor(Math.random() * names.length);\r\n \tvar randomIndex2 = Math.floor(Math.random() * names.length);\r\n"
                },
                {
                    "date": 1682999455090,
                    "content": "Index: \n===================================================================\n--- \n+++ \n@@ -26,9 +26,9 @@\n \tvar randomName1 = names[randomIndex1];\r\n \tvar randomName2 = names[randomIndex2];\r\n \r\n \t// construct the message\r\n-\tvar message = \"Hello \" + firstname + \" \" + lastname + \", you are a \" + selected.join(\", \") + \" little jerk, and \" + selectedOption + \" . Your new name is \" + randomName1 + \" \" + randomName2 + \".\";\r\n+\tvar message = \"Hello \" + firstname + \" \" + lastname + \", you are a \" + selected.join(\", \") + \" little jerk, and \" + selectedOption + \". Your new name is \" + randomName1 + \" \" + randomName2 + \".\";\r\n \r\n \t// display the message in an alert box\r\n \talert(message);\r\n }\r\n"
                },
                {
                    "date": 1683000131578,
                    "content": "Index: \n===================================================================\n--- \n+++ \n@@ -26,9 +26,9 @@\n \tvar randomName1 = names[randomIndex1];\r\n \tvar randomName2 = names[randomIndex2];\r\n \r\n \t// construct the message\r\n-\tvar message = \"Hello \" + firstname + \" \" + lastname + \", you are a \" + selected.join(\", \") + \" little jerk, and \" + selectedOption + \". Your new name is \" + randomName1 + \" \" + randomName2 + \".\";\r\n+\tvar message = \"Hello \" + firstname + \" \" + lastname + \", you are a \" + selected.join(\", \") + \" little jerk, and \" + selectedOption + \". You have lost the right to use the name \" + firstname + \" \" + lastname + \". You will be henceforth know as \" + randomName1 + \" \" + randomName2 + \". May shame follow your family for 1000 years.\";\r\n \r\n \t// display the message in an alert box\r\n \talert(message);\r\n }\r\n"
                },
                {
                    "date": 1683000167104,
                    "content": "Index: \n===================================================================\n--- \n+++ \n@@ -26,9 +26,9 @@\n \tvar randomName1 = names[randomIndex1];\r\n \tvar randomName2 = names[randomIndex2];\r\n \r\n \t// construct the message\r\n-\tvar message = \"Hello \" + firstname + \" \" + lastname + \", you are a \" + selected.join(\", \") + \" little jerk, and \" + selectedOption + \". You have lost the right to use the name \" + firstname + \" \" + lastname + \". You will be henceforth know as \" + randomName1 + \" \" + randomName2 + \". May shame follow your family for 1000 years.\";\r\n+\tvar message = \"Hello \" + firstname + \" \" + lastname + \", you are a \" + selected.join(\", \") + \" little jerk, and \" + selectedOption + \". You have lost the right to use the name \" + firstname + \" \" + lastname + \", you nerd. You will be henceforth know as \" + randomName1 + \" \" + randomName2 + \". May shame follow your family for 1000 years.\";\r\n \r\n \t// display the message in an alert box\r\n \talert(message);\r\n }\r\n"
                },
                {
                    "date": 1683000305712,
                    "content": "Index: \n===================================================================\n--- \n+++ \n@@ -26,9 +26,9 @@\n \tvar randomName1 = names[randomIndex1];\r\n \tvar randomName2 = names[randomIndex2];\r\n \r\n \t// construct the message\r\n-\tvar message = \"Hello \" + firstname + \" \" + lastname + \", you are a \" + selected.join(\", \") + \" little jerk, and \" + selectedOption + \". You have lost the right to use the name \" + firstname + \" \" + lastname + \", you nerd. You will be henceforth know as \" + randomName1 + \" \" + randomName2 + \". May shame follow your family for 1000 years.\";\r\n+\tvar message = \"Hey \" + firstname + \" \" + lastname + \"! Here's a message to cheer you up! You are an \" + selected.join(\", \") + \" little jerk, and \" + selectedOption + \". You have lost the right to use the name \" + firstname + \" \" + lastname + \", you nerd. You will be henceforth knownS as \" + randomName1 + \" \" + randomName2 + \". May shame follow your family for 1000 years.\";\r\n \r\n \t// display the message in an alert box\r\n \talert(message);\r\n }\r\n"
                },
                {
                    "date": 1683000354618,
                    "content": "Index: \n===================================================================\n--- \n+++ \n@@ -26,9 +26,9 @@\n \tvar randomName1 = names[randomIndex1];\r\n \tvar randomName2 = names[randomIndex2];\r\n \r\n \t// construct the message\r\n-\tvar message = \"Hey \" + firstname + \" \" + lastname + \"! Here's a message to cheer you up! You are an \" + selected.join(\", \") + \" little jerk, and \" + selectedOption + \". You have lost the right to use the name \" + firstname + \" \" + lastname + \", you nerd. You will be henceforth knownS as \" + randomName1 + \" \" + randomName2 + \". May shame follow your family for 1000 years.\";\r\n+\tvar message = \"Hey \" + firstname + \" \" + lastname + \"! Here's a message to cheer you up! You are an \" + selected.join(\", \") + \" little jerk, and \" + selectedOption + \". You have lost the right to use the name \" + firstname + \" \" + lastname + \", you nerd. You will be henceforth known as \" + randomName1 + \" \" + randomName2 + \". May shame follow your family for 1000 years.\";\r\n \r\n \t// display the message in an alert box\r\n \talert(message);\r\n }\r\n"
                },
                {
                    "date": 1683000430606,
                    "content": "Index: \n===================================================================\n--- \n+++ \n@@ -26,9 +26,9 @@\n \tvar randomName1 = names[randomIndex1];\r\n \tvar randomName2 = names[randomIndex2];\r\n \r\n \t// construct the message\r\n-\tvar message = \"Hey \" + firstname + \" \" + lastname + \"! Here's a message to cheer you up! You are an \" + selected.join(\", \") + \" little jerk, and \" + selectedOption + \". You have lost the right to use the name \" + firstname + \" \" + lastname + \", you nerd. You will be henceforth known as \" + randomName1 + \" \" + randomName2 + \". May shame follow your family for 1000 years.\";\r\n+\tvar message = \"Hey \" + firstname + \" \" + lastname + \"! Here's a message to cheer you up! You are an \" + selected.join(\", \") + \" little jerk, and \" + selectedOption + \".\" + \"/n You have lost the right to use the name \" + firstname + \" \" + lastname + \", you nerd. You will be henceforth known as \" + randomName1 + \" \" + randomName2 + \". May shame follow your family for 1000 years.\";\r\n \r\n \t// display the message in an alert box\r\n \talert(message);\r\n }\r\n"
                },
                {
                    "date": 1683000517771,
                    "content": "Index: \n===================================================================\n--- \n+++ \n@@ -26,9 +26,9 @@\n \tvar randomName1 = names[randomIndex1];\r\n \tvar randomName2 = names[randomIndex2];\r\n \r\n \t// construct the message\r\n-\tvar message = \"Hey \" + firstname + \" \" + lastname + \"! Here's a message to cheer you up! You are an \" + selected.join(\", \") + \" little jerk, and \" + selectedOption + \".\" + \"/n You have lost the right to use the name \" + firstname + \" \" + lastname + \", you nerd. You will be henceforth known as \" + randomName1 + \" \" + randomName2 + \". May shame follow your family for 1000 years.\";\r\n+\tvar message = \"Hey \" + firstname + \" \" + lastname + \"! Here's a message to cheer you up! You are an \" + selected.join(\", \") + \" little jerk, and \" + selectedOption + \".\" + \"<br> You have lost the right to use the name \" + firstname + \" \" + lastname + \", you nerd. You will be henceforth known as \" + randomName1 + \" \" + randomName2 + \". May shame follow your family for 1000 years.\";\r\n \r\n \t// display the message in an alert box\r\n \talert(message);\r\n }\r\n"
                },
                {
                    "date": 1683000539541,
                    "content": "Index: \n===================================================================\n--- \n+++ \n@@ -26,9 +26,9 @@\n \tvar randomName1 = names[randomIndex1];\r\n \tvar randomName2 = names[randomIndex2];\r\n \r\n \t// construct the message\r\n-\tvar message = \"Hey \" + firstname + \" \" + lastname + \"! Here's a message to cheer you up! You are an \" + selected.join(\", \") + \" little jerk, and \" + selectedOption + \".\" + \"<br> You have lost the right to use the name \" + firstname + \" \" + lastname + \", you nerd. You will be henceforth known as \" + randomName1 + \" \" + randomName2 + \". May shame follow your family for 1000 years.\";\r\n+\tvar message = \"Hey \" + firstname + \" \" + lastname + \"! Here's a message to cheer you up! You are an \" + selected.join(\", \") + \" little jerk, and \" + selectedOption + \". You have lost the right to use the name \" + firstname + \" \" + lastname + \", you nerd. You will be henceforth known as \" + randomName1 + \" \" + randomName2 + \". May shame follow your family for 1000 years.\";\r\n \r\n \t// display the message in an alert box\r\n \talert(message);\r\n }\r\n"
                },
                {
                    "date": 1683000617989,
                    "content": "Index: \n===================================================================\n--- \n+++ \n@@ -26,9 +26,9 @@\n \tvar randomName1 = names[randomIndex1];\r\n \tvar randomName2 = names[randomIndex2];\r\n \r\n \t// construct the message\r\n-\tvar message = \"Hey \" + firstname + \" \" + lastname + \"! Here's a message to cheer you up! You are an \" + selected.join(\", \") + \" little jerk, and \" + selectedOption + \". You have lost the right to use the name \" + firstname + \" \" + lastname + \", you nerd. You will be henceforth known as \" + randomName1 + \" \" + randomName2 + \". May shame follow your family for 1000 years.\";\r\n+\tvar message = \"Hey \" + firstname + \" \" + lastname + \"! Here's a message to cheer you up! You are an \" + selected.join(\", \") + \" little jerk, and \" + selectedOption + \". \\nYou have lost the right to use the name \" + firstname + \" \" + lastname + \", you nerd. You will be henceforth known as \" + randomName1 + \" \" + randomName2 + \". May shame follow your family for 1000 years.\";\r\n \r\n \t// display the message in an alert box\r\n \talert(message);\r\n }\r\n"
                }
            ],
            "date": 1682991564597,
            "name": "Commit-0",
            "content": "function displayMessage() {\r\n\talert(\"test\");\r\n}\r\n"
        }
    ]
}